{
  "main": {
    "id": "337d25e05a864f1a",
    "type": "split",
    "children": [
      {
        "id": "c4f6f7b30403584d",
        "type": "tabs",
        "children": [
          {
            "id": "1fd1c9a5e36978fb",
            "type": "leaf",
            "state": {
              "type": "markdown",
              "state": {
                "file": "00-daily/2025-07-03.md",
                "mode": "source",
                "source": false
              },
              "icon": "lucide-file",
              "title": "2025-07-03"
            }
          },
          {
            "id": "bcef6dcf9f24ee0d",
            "type": "leaf",
            "state": {
              "type": "markdown",
              "state": {
                "file": "GEMINI.md",
                "mode": "source",
                "source": false
              },
              "icon": "lucide-file",
              "title": "GEMINI"
            }
          }
        ],
        "currentTab": 1
      }
    ],
    "direction": "vertical"
  },
  "left": {
    "id": "191c86b445698739",
    "type": "split",
    "children": [
      {
        "id": "90a653bb80647bb4",
        "type": "tabs",
        "children": [
          {
            "id": "374aee939632b657",
            "type": "leaf",
            "state": {
              "type": "file-explorer",
              "state": {
                "sortOrder": "byCreatedTime",
                "autoReveal": false
              },
              "icon": "lucide-folder-closed",
              "title": "ファイルエクスプローラ"
            }
          },
          {
            "id": "abf0025f7f9bb0c3",
            "type": "leaf",
            "state": {
              "type": "search",
              "state": {
                "query": "tag:#量子重力",
                "matchingCase": false,
                "explainSearch": false,
                "collapseAll": false,
                "extraContext": false,
                "sortOrder": "alphabetical"
              },
              "icon": "lucide-search",
              "title": "検索"
            }
          },
          {
            "id": "3d3fdcc2808bcaa3",
            "type": "leaf",
            "state": {
              "type": "bookmarks",
              "state": {},
              "icon": "lucide-bookmark",
              "title": "ブックマーク"
            }
          }
        ]
      }
    ],
    "direction": "horizontal",
    "width": 200
  },
  "right": {
    "id": "4fe5bf4a1136af91",
    "type": "split",
    "children": [
      {
        "id": "078644e56e397c3c",
        "type": "tabs",
        "children": [
          {
            "id": "0449ba7d3c7307b4",
            "type": "leaf",
            "state": {
              "type": "backlink",
              "state": {
                "file": "00-daily/2025-07-04.md",
                "collapseAll": false,
                "extraContext": false,
                "sortOrder": "alphabetical",
                "showSearch": false,
                "searchQuery": "",
                "backlinkCollapsed": false,
                "unlinkedCollapsed": true
              },
              "icon": "links-coming-in",
              "title": "2025-07-04へのバックリンク"
            }
          },
          {
            "id": "65847a1255ee62b9",
            "type": "leaf",
            "state": {
              "type": "outgoing-link",
              "state": {
                "file": "Welcome.md",
                "linksCollapsed": false,
                "unlinkedCollapsed": true
              },
              "icon": "links-going-out",
              "title": "Welcomeからのアウトゴーイングリンク"
            }
          },
          {
            "id": "89cbab424b9b9b54",
            "type": "leaf",
            "state": {
              "type": "tag",
              "state": {
                "sortOrder": "frequency",
                "useHierarchy": true,
                "showSearch": false,
                "searchQuery": ""
              },
              "icon": "lucide-tags",
              "title": "タグ"
            }
          },
          {
            "id": "48af92efd8447835",
            "type": "leaf",
            "state": {
              "type": "outline",
              "state": {
                "file": "00-daily/2025-07-04.md",
                "followCursor": false,
                "showSearch": false,
                "searchQuery": ""
              },
              "icon": "lucide-list",
              "title": "2025-07-04のアウトライン"
            }
          },
          {
            "id": "4883964bea3fded9",
            "type": "leaf",
            "state": {
              "type": "smart-connections-view",
              "state": {},
              "icon": "smart-connections",
              "title": "Smart Connections"
            }
          },
          {
            "id": "784d42ac30280e47",
            "type": "leaf",
            "state": {
              "type": "smart-connections-visualizer",
              "state": {},
              "icon": "git-fork",
              "title": "Smart connections visualizer"
            }
          }
        ],
        "currentTab": 2
      }
    ],
    "direction": "horizontal",
    "width": 447.5,
    "collapsed": true
  },
  "left-ribbon": {
    "hiddenItems": {
      "markdown-importer:Markdownインポーターを開く": false,
      "random-note:ランダムノートを開く": false,
      "switcher:クイックスイッチャーを開く": false,
      "graph:グラフビューを開く": false,
      "canvas:新規キャンバスを作成": false,
      "daily-notes:今日のデイリーノートを開く": false,
      "templates:テンプレートを挿入": false,
      "command-palette:コマンドパレットを開く": false,
      "github-sync:Sync with Remote": false,
      "mermaid-tools:Open Mermaid Toolbar": false,
      "smart-connections:Open: Smart Chat": false,
      "smart-connections:Open: View Smart Connections": false,
      "smart-connections-visualizer:Open smart connections visualizer": false,
      "templater-obsidian:Templater": false
    }
  },
  "active": "bcef6dcf9f24ee0d",
  "lastOpenFiles": [
    "10-inbox/Professional Cloud Architect問題解説.md",
    "10-inbox/マイクロサービス負荷検証Geminiさんの見解.md",
    "10-inbox/Ornstein-Uhlenbeck過程とそのFokker-Planck方程式による解法まとめ.md",
    "00-daily/2025-07-08.md",
    "00-daily/2025-07-03.md",
    "40-templates/daily.md",
    "40-templates/inbox.md",
    "00-daily/2026-07-02.md",
    "00-daily/2025-07-04.md",
    "00-daily/2025-07-07.md",
    "GEMINI.md",
    "運用ルール.md",
    "README.md",
    "Fokker-Planck方程式をPINNの方法で解析的に.md",
    "無題のファイル.md",
    "11-inbox-book/20世紀科学論文集　現代宇宙論の誕生.md",
    "20-permanent/インフレーションのクラス再考.md",
    "20-permanent/アルビレオAの視線速度変化から探る新たな伴星.md",
    "10-inbox/Dockerのベストプラクティス翻訳.md",
    "無題のフォルダ",
    "50-resource/スクリーンショット 2025-07-07 15.02.56.png",
    "10-inbox/ランダムグラフに対する最小作用の原理.md",
    "10-inbox/アルビレオAの視線速度変化から探る新たな伴星.md",
    "10-inbox/連星アルビレオについて科学館で聞いた話.md",
    "20-permanent/Shiniseチームconfig.md",
    "20-permanent/K8sにおけるPostgreSQL接続エラーのトラブルシューティングプロセス.md",
    "10-inbox/インフレーションのクラス再考.md",
    "10-inbox/生成消滅演算子関連の公式集.md",
    "50-resource/スクリーンショット 2025-07-04 16.20.25.png",
    "50-resource",
    "スクリーンショット 2025-07-04 16.20.25.png",
    "11-inbox-book",
    "test",
    "30-projects",
    "40-templates",
    "無題のファイル.canvas",
    "20-permanent",
    "10-inbox",
    "01-weekly",
    "00-daily"
  ]
}